yaschedule/__init__.py
yaschedule/core.py
yaschedule-0.0.4.0.dist-info/LICENSE
yaschedule-0.0.4.0.dist-info/METADATA
yaschedule-0.0.4.0.dist-info/WHEEL
yaschedule-0.0.4.0.dist-info/top_level.txt
yaschedule-0.0.4.0.dist-info/RECORD
