Metadata-Version: 2.1
Name: yaschedule
Version: 0.0.4.0
Summary: Lib for getting schedule data from Yandex.Rasp API
Home-page: https://github.com/StannisGr/yaschedule
Author: StannisGr
Author-email: bvc344@gmail.com
License: Apache License 2.0
Keywords: yandex,schedule,api,yandex.rasp
Platform: any
License-File: LICENSE
Requires-Dist: certifi (>=2021.10.8)
Requires-Dist: charset-normalizer (>=2.0.12)
Requires-Dist: idna (>=3.3)
Requires-Dist: requests (>=2.27.1)
Requires-Dist: urllib3 (>=1.26.9)
